barcodenumber/__init__.py
barcodenumber/gs1datamatrix.py
barcodenumber/tests.py
barcodenumber-0.4.0.dist-info/LICENSE
barcodenumber-0.4.0.dist-info/METADATA
barcodenumber-0.4.0.dist-info/WHEEL
barcodenumber-0.4.0.dist-info/top_level.txt
barcodenumber-0.4.0.dist-info/RECORD
