Metadata-Version: 2.1
Name: barcodenumber
Version: 0.4.0
Summary: Python module to validate Product codes (EAN, EAN13, ISBN,...)
Home-page: http://www.zikzakmedia.com/
Author: Zikzakmedia SL
Author-email: zikzak@zikzakmedia.com
License: GPL-3
Download-URL: https://bitbucket.org/zikzakmedia/python-barcodenumber
Platform: UNKNOWN
Classifier: Development Status :: 5 - Production/Stable
Classifier: Intended Audience :: Developers
Classifier: License :: OSI Approved :: GNU General Public License (GPL)
Classifier: Operating System :: OS Independent
Classifier: Programming Language :: Python :: 2.7
Classifier: Programming Language :: Python :: 3.3
Classifier: Programming Language :: Python :: 3.4
Classifier: Programming Language :: Python :: 3.5
Classifier: Programming Language :: Python :: 3.6
Classifier: Programming Language :: Python :: 3.7
Classifier: Topic :: Software Development :: Libraries :: Python Modules
Requires-Dist: python-stdnum
